{
  "B09S294TGM": {
    "weekStart": "2026-03-16",
    "totalCount": 3429,
    "positiveCount": 3018,
    "negativeCount": 411
  },
  "B09S2LSQ4D": {
    "weekStart": "2026-03-16",
    "totalCount": 327,
    "positiveCount": 278,
    "negativeCount": 49
  },
  "B09S2G3ZPP": {
    "weekStart": "2026-03-16",
    "totalCount": 17,
    "positiveCount": 14,
    "negativeCount": 3
  },
  "B09S27FV5F": {
    "weekStart": "2026-03-16",
    "totalCount": 2503,
    "positiveCount": 2178,
    "negativeCount": 325
  }
}